swepin/__init__.py
swepin/example.py
swepin/exceptions.py
swepin/generate.py
swepin/loose.py
swepin/strict.py
swepin-1.1.4.dist-info/licenses/LICENSE
swepin-1.1.4.dist-info/METADATA
swepin-1.1.4.dist-info/WHEEL
swepin-1.1.4.dist-info/top_level.txt
swepin-1.1.4.dist-info/RECORD
