Metadata-Version: 2.4
Name: swepin
Version: 1.1.4
Summary: Environment variable helpers
Author-email: Erik Bremstedt <erik.bremstedt@gmail.com>
Project-URL: Homepage, https://github.com/ebremstedt/swepin
Project-URL: Issues, https://github.com/ebremstedt/swepin/issues
Classifier: Programming Language :: Python :: 3
Classifier: License :: OSI Approved :: MIT License
Classifier: Operating System :: OS Independent
Requires-Python: >=3.10
License-File: LICENSE
Dynamic: license-file
